README.rst
setup.cfg
setup.py
wowair/__init__.py
wowair/config.py
wowair/error.py
wowair/flight.py
wowair/query.py
wowair/thread.py
wowair.egg-info/PKG-INFO
wowair.egg-info/SOURCES.txt
wowair.egg-info/dependency_links.txt
wowair.egg-info/requires.txt
wowair.egg-info/top_level.txt