Metadata-Version: 1.1
Name: wowair
Version: 0.5
Summary: WowAir Python API
Home-page: https://github.com/acupy/wowair_api
Author: Adam Czuprak
Author-email: adam.czuprak@hotmail.com
License: MIT
Download-URL: https://github.com/acupy/wowair_api/archive/0.5.tar.gz
Keywords: wowair,api
Platform: UNKNOWN
